polaris/__init__.py
polaris/core/__init__.py
polaris/core/poles.py
polaris/core/statespace.py
polaris/core/transfer.py
polaris/excitation/__init__.py
polaris/excitation/basic.py
polaris/py.typed
polaris/reference/__init__.py
polaris/reference/rbj.py
polaris/signal/__init__.py
polaris/signal/normalize.py
polaris_audio-0.1.0.dist-info/WHEEL
polaris_audio-0.1.0.dist-info/METADATA
polaris_audio-0.1.0.dist-info/RECORD
