Metadata-Version: 2.3
Name: polaris-audio
Version: 0.1.0
Summary: Control-theoretic DSP tools for pole-based sound synthesis and analysis.
Author: inaba1115
Author-email: inaba1115 <inaba1115@gmail.com>
Classifier: Development Status :: 3 - Alpha
Classifier: Intended Audience :: Science/Research
Classifier: Topic :: Scientific/Engineering
Classifier: Topic :: Multimedia :: Sound/Audio
Classifier: License :: OSI Approved :: MIT License
Classifier: Programming Language :: Python :: 3
Classifier: Programming Language :: Python :: 3.10
Classifier: Programming Language :: Python :: 3.11
Requires-Dist: numpy>=2.2.6
Requires-Python: >=3.10
